{
  "rectangleList": [
    {
      "width": 1.166241059E9,
      "length": 1.884421551E9
    },
    {
      "width": 1.57521026E9,
      "length": 1.390599143E9
    },
    {
      "width": 1.326447147E9,
      "length": 1.247994954E9
    },
    {
      "width": 1.608482296E9,
      "length": 8.1782516E7
    },
    {
      "width": 6.10934678E8,
      "length": 1.921316645E9
    },
    {
      "width": 7.96645238E8,
      "length": 6.30751611E8
    },
    {
      "width": 1.480314342E9,
      "length": 9.31235803E8
    },
    {
      "width": 1.75374232E9,
      "length": 1.245273826E9
    }
  ]
}