<?xml version="1.0" encoding="UTF-8" standalone="yes"?>
<triangles>
    <triangle>
        <a>3.0</a>
        <b>4.0</b>
        <c>5.0</c>
    </triangle>
    <triangle>
        <a>6.56538246E8</a>
        <b>5.29718941E8</b>
        <c>1.511946973E9</c>
    </triangle>
    <triangle>
        <a>1.253568754E9</a>
        <b>1.107715545E9</b>
        <c>1.293994067E9</c>
    </triangle>
    <triangle>
        <a>4.33061571E8</a>
        <b>1.95826823E8</b>
        <c>1.720456213E9</c>
    </triangle>
    <triangle>
        <a>4.74694755E8</a>
        <b>5.85878127E8</b>
        <c>6.71560264E8</c>
    </triangle>
    <triangle>
        <a>4.83366379E8</a>
        <b>1.00447065E8</b>
        <c>1.894896629E9</c>
    </triangle>
    <triangle>
        <a>1.740827902E9</a>
        <b>1.107602669E9</b>
        <c>1.294418607E9</c>
    </triangle>
    <triangle>
        <a>1.44028059E9</a>
        <b>9.16565158E8</b>
        <c>1.435630657E9</c>
    </triangle>
    <triangle>
        <a>1.011609591E9</a>
        <b>2.081454002E9</b>
        <c>9.72978579E8</c>
    </triangle>
    <triangle>
        <a>1.688282401E9</a>
        <b>1.77125277E8</b>
        <c>5.95229698E8</c>
    </triangle>
    <triangle>
        <a>1.457441933E9</a>
        <b>9.11437092E8</b>
        <c>1.18297571E9</c>
    </triangle>
    <triangle>
        <a>5.83721574E8</a>
        <b>1.404795892E9</b>
        <c>4.2952468E7</c>
    </triangle>
    <triangle>
        <a>8.39486353E8</a>
        <b>5.3356216E8</b>
        <c>2.074642055E9</c>
    </triangle>
    <triangle>
        <a>8.52714506E8</a>
        <b>3.56679431E8</b>
        <c>1.70541072E9</c>
    </triangle>
    <triangle>
        <a>2.02306177E9</a>
        <b>6.93135523E8</b>
        <c>4.9779134E7</c>
    </triangle>
    <triangle>
        <a>1.358696144E9</a>
        <b>1.361352451E9</b>
        <c>2.111499177E9</c>
    </triangle>
    <triangle>
        <a>1.263502326E9</a>
        <b>1.841273023E9</b>
        <c>1.890132388E9</c>
    </triangle>
    <triangle>
        <a>1.09071994E9</a>
        <b>1.385765986E9</b>
        <c>1.620562428E9</c>
    </triangle>
    <triangle>
        <a>2.13075154E9</a>
        <b>8.82068594E8</b>
        <c>8.1965172E7</c>
    </triangle>
    <triangle>
        <a>1.135032596E9</a>
        <b>1.22480886E8</b>
        <c>2.088850861E9</c>
    </triangle>
    <triangle>
        <a>1.329944729E9</a>
        <b>3.94089048E8</b>
        <c>6.20002032E8</c>
    </triangle>
</triangles>
