<?xml version='1.0' encoding='utf-8'?>
<job-scheduling-data xmlns="http://www.quartz-scheduler.org/xml/JobSchedulingData" xmlns:xsi="http://www.w3.org/2001/XMLSchema-instance" xsi:schemaLocation="http://www.quartz-scheduler.org/xml/JobSchedulingData http://www.quartz-scheduler.org/xml/job_scheduling_data_1_8.xsd" version="1.8">
    <schedule>
    <job>
        <name>myJob</name>
        <group>group1</group>
        <job-class>ge.ufc.webapps.TriangleJob</job-class>
        <job-data-map>
            <entry>
                <key>path</key>
                <value>C:\\Program Files\\Apache Software Foundation\\Tomcat 8.5\\conf\\triangles\\triangles.xml</value>
            </entry>
            <entry>
                <key>X</key>
                <value>1</value>
            </entry>
        </job-data-map>
    </job>
     <trigger>
        <simple>
            <name>myJobTrigger</name>
            <group>group1</group>
            <job-name>myJob</job-name>
            <job-group>group1</job-group>
            <repeat-count>15</repeat-count>
            <repeat-interval>60000</repeat-interval>
        </simple>
    </trigger>
</schedule>
</job-scheduling-data>